meta_agent/__init__.py
meta_agent-0.1.0.dist-info/LICENSE
meta_agent-0.1.0.dist-info/METADATA
meta_agent-0.1.0.dist-info/WHEEL
meta_agent-0.1.0.dist-info/RECORD
